pyKoalaRemote/__init__.py
pyKoalaRemote/client.py
pyKoalaRemote/remote_utils.py
pykoalaremote-1.2.0.dist-info/licenses/LICENSE
pykoalaremote-1.2.0.dist-info/METADATA
pykoalaremote-1.2.0.dist-info/WHEEL
pykoalaremote-1.2.0.dist-info/top_level.txt
pykoalaremote-1.2.0.dist-info/RECORD
