Metadata-Version: 2.4
Name: pyKoalaRemote
Version: 1.2.0
Summary: Python wrapper for dotNet Koala Remote Client provided by LyncéeTec to control Digital Holographique Microscope using proprietary Koala software
Home-page: https://github.com/lynceetec/pyKoalaRemote
Author: Software Team: J. Parent - F. Mendels - T. Colomb
Author-email: software@lynceetec.com
Classifier: Programming Language :: Python :: 3
Classifier: License :: OSI Approved :: MIT License
Classifier: Operating System :: Microsoft :: Windows
License-File: LICENSE
Dynamic: author
Dynamic: author-email
Dynamic: classifier
Dynamic: description
Dynamic: description-content-type
Dynamic: home-page
Dynamic: license-file
Dynamic: summary
